jerrypycia/.DS_Store
jerrypycia/__init__.py
jerrypycia/datasets/GratefulDead.csv
jerrypycia/jerryPycia.py
jerrypycia-0.1.5.dist-info/WHEEL
jerrypycia-0.1.5.dist-info/METADATA
jerrypycia-0.1.5.dist-info/RECORD
