Metadata-Version: 2.1
Name: jerrypycia
Version: 0.1.5
Summary: 
Author: Andrew Blance
Author-email: andrewblance@live.co.uk
Requires-Python: >=3.6.1,<4.0.0
Classifier: Programming Language :: Python :: 3
Classifier: Programming Language :: Python :: 3.7
Requires-Dist: matplotlib (>=3.2,<4.0)
Requires-Dist: pandas (>=1.0,<2.0)
